pyside2_style_test/__init__.py
pyside2_style_test/__main__.py
pyside2_style_test/cli.py
m3tior_pyside2_style_test-0.9.3.dist-info/LICENSE
m3tior_pyside2_style_test-0.9.3.dist-info/METADATA
m3tior_pyside2_style_test-0.9.3.dist-info/WHEEL
m3tior_pyside2_style_test-0.9.3.dist-info/entry_points.txt
m3tior_pyside2_style_test-0.9.3.dist-info/top_level.txt
m3tior_pyside2_style_test-0.9.3.dist-info/RECORD
