Metadata-Version: 2.1
Name: m3tior-pyside2-style-test
Version: 0.9.3
Summary: A Qt-5 interactive stylesheet preview script
Home-page: https://github.com/m3tior/pyside2-style-test
Author: Ruby Allison Rose (aka: M3TIOR)
Author-email: cplusplusook@gmail.com
License: MIT
Platform: UNKNOWN
Classifier: Programming Language :: Python :: 3.5
Classifier: License :: OSI Approved :: MIT License
Classifier: Operating System :: OS Independent
Requires-Dist: PySide2 (==5.12.1)
